[
  {
    "id": 0,
    "age": 4,
    "vaccinated": true,
    "image": "dog-doberman.png",
    "name": "Doberman",
    "description": "Świetny nowy przyjaciel dla całej rodziny. Chroni i uwielbia",
    "tag": "Pies",
    "subTag": "Drapieżnik",
    "price": "5 770zł",
    "filterType": 1
  },
  {
    "id": 1,
    "age": 3,
    "vaccinated": true,
    "image": "cat-wesl.png",
    "name": "Kot z krzywymi uszami",
    "description": "Idealna dziewczyna na deszczowe zimne czasy",
    "tag": "Koty",
    "subTag": null,
    "price": "6 370zł",
    "filterType": 2
  },
  {
    "id": 2,
    "age": 4,
    "vaccinated": false,
    "image": "parrot-ara.png",
    "name": "Papuga ara",
    "description": "Zwierzak, który nie sprawi, że się znudzisz",
    "tag": "Papugi",
    "subTag": "Drapieżnik",
    "price": "2 710zł",
    "filterType": 3
  },
  {
    "id": 3,
    "age": 4,
    "vaccinated": true,
    "image": "dog-doberman.png",
    "name": "Doberman",
    "description": "Świetny nowy przyjaciel dla całej rodziny. Chroni i uwielbia",
    "tag": "Pies",
    "subTag": "Drapieżnik",
    "price": "2 110zł",
    "filterType": 1
  },
  {
    "id": 4,
    "age": 3,
    "vaccinated": true,
    "image": "cat-wesl.png",
    "name": "Kot z krzywymi uszami",
    "description": "Idealna dziewczyna na deszczowe zimne czasy",
    "tag": "Koty",
    "subTag": null,
    "price": "1 580zł",
    "filterType": 2
  },
  {
    "id": 5,
    "age": 4,
    "vaccinated": false,
    "image": "parrot-ara.png",
    "name": "Papuga ara",
    "description": "Zwierzak, który nie sprawi, że się znudzisz",
    "tag": "Papugi",
    "subTag": "Drapieżnik",
    "price": "3 270zł",
    "filterType": 3
  },
  {
    "id": 6,
    "age": 4,
    "vaccinated": true,
    "image": "dog-doberman.png",
    "name": "Doberman",
    "description": "Świetny nowy przyjaciel dla całej rodziny. Chroni i uwielbia",
    "tag": "Pies",
    "subTag": "Drapieżnik",
    "price": "4 760zł",
    "filterType": 1
  },
  {
    "id": 7,
    "age": 3,
    "vaccinated": true,
    "image": "cat-wesl.png",
    "name": "Kot z krzywymi uszami",
    "description": "Idealna dziewczyna na deszczowe zimne czasy",
    "tag": "Koty",
    "subTag": null,
    "price": "4 270zł",
    "filterType": 2
  },
  {
    "id": 8,
    "age": 4,
    "vaccinated": false,
    "image": "parrot-ara.png",
    "name": "Papuga ara",
    "description": "Zwierzak, który nie sprawi, że się znudzisz",
    "tag": "Papugi",
    "subTag": "Drapieżnik",
    "price": "2 770zł",
    "filterType": 3
  },
  {
    "id": 9,
    "age": 4,
    "vaccinated": true,
    "image": "dog-doberman.png",
    "name": "Doberman",
    "description": "Świetny nowy przyjaciel dla całej rodziny. Chroni i uwielbia",
    "tag": "Pies",
    "subTag": "Drapieżnik",
    "price": "1 770zł",
    "filterType": 1
  },
  {
    "id": 10,
    "age": 3,
    "vaccinated": true,
    "image": "cat-wesl.png",
    "name": "Kot z krzywymi uszami",
    "description": "Idealna dziewczyna na deszczowe zimne czasy",
    "tag": "Koty",
    "subTag": null,
    "price": "7 770zł",
    "filterType": 2
  },
  {
    "id": 11,
    "age": 4,
    "vaccinated": false,
    "image": "parrot-ara.png",
    "name": "Papuga ara",
    "description": "Zwierzak, który nie sprawi, że się znudzisz",
    "tag": "Papugi",
    "subTag": "Drapieżnik",
    "price": "4 770zł",
    "filterType": 3
  }
]
